fastapi_ormar_utilities/__init__.py
fastapi_ormar_utilities/base.py
fastapi_ormar_utilities/decorators.py
fastapi_ormar_utilities-0.1.1.dist-info/METADATA
fastapi_ormar_utilities-0.1.1.dist-info/WHEEL
fastapi_ormar_utilities-0.1.1.dist-info/top_level.txt
fastapi_ormar_utilities-0.1.1.dist-info/RECORD
