Metadata-Version: 2.1
Name: fastapi-ormar-utilities
Version: 0.1.1
Summary: Small, but usefull library for interaction with Ormar ORM
Home-page: https://github.com/vladisa88/fastapi-ormar-utilities
Author: Vladislav Isakov
Author-email: vladisa88@gmail.com
License: UNKNOWN
Keywords: python,ormar,async,fastapi,pydantic
Platform: UNKNOWN
Classifier: Development Status :: 3 - Alpha
Classifier: Programming Language :: Python
Classifier: Programming Language :: Python :: 3
Classifier: Programming Language :: Python :: 3.8
Classifier: Programming Language :: Python :: 3.9
Classifier: Operating System :: OS Independent
Classifier: Topic :: Internet
Classifier: Topic :: Office/Business
Classifier: Topic :: Software Development :: Libraries
Requires-Dist: pydantic
Requires-Dist: ormar
Requires-Dist: fastapi
